skstep/__init__.py
skstep/_base.py
skstep/_gauss.py
skstep/_moments.py
skstep/_poisson.py
skstep/_results.py
skstep/_sample.py
skstep/_ttest.py
skstep/_utils.py
scikit_step-0.1.0.dist-info/METADATA
scikit_step-0.1.0.dist-info/WHEEL
scikit_step-0.1.0.dist-info/licenses/LICENSE
scikit_step-0.1.0.dist-info/RECORD
