Metadata-Version: 2.3
Name: scikit-step
Version: 0.1.0
Summary: 1-D step detection algorithms
Project-URL: Download, https://github.com/hanjinliu/scikit-step
Author-email: Hanjin Liu <liuhanjin-sc@g.ecc.u-tokyo.ac.jp>
License: MIT License
License-File: LICENSE
Requires-Python: >=3.8
Requires-Dist: numpy>=1.21
Requires-Dist: scipy>=1.7.3
Provides-Extra: all
Requires-Dist: dask>=2021.11.1; extra == 'all'
Requires-Dist: matplotlib>=3.1; extra == 'all'
